odoo/addons/l10n_be_vat_reports/README.rst
odoo/addons/l10n_be_vat_reports/__init__.py
odoo/addons/l10n_be_vat_reports/__manifest__.py
odoo/addons/l10n_be_vat_reports/i18n/l10n_be_vat_reports.pot
odoo/addons/l10n_be_vat_reports/readme/CONTRIBUTORS.rst
odoo/addons/l10n_be_vat_reports/readme/DESCRIPTION.rst
odoo/addons/l10n_be_vat_reports/reports/be_vat_client_listing_consignment.xml
odoo/addons/l10n_be_vat_reports/reports/be_vat_client_listing_consignment.xsd
odoo/addons/l10n_be_vat_reports/reports/be_vat_declarant.xml
odoo/addons/l10n_be_vat_reports/reports/be_vat_intra_consignment.xml
odoo/addons/l10n_be_vat_reports/reports/be_vat_intra_consignment.xsd
odoo/addons/l10n_be_vat_reports/reports/l10n_be_reports.xml
odoo/addons/l10n_be_vat_reports/security/ir.model.access.csv
odoo/addons/l10n_be_vat_reports/static/description/icon.png
odoo/addons/l10n_be_vat_reports/static/description/index.html
odoo/addons/l10n_be_vat_reports/tests/__init__.py
odoo/addons/l10n_be_vat_reports/tests/common.py
odoo/addons/l10n_be_vat_reports/tests/test_vat_intra.py
odoo/addons/l10n_be_vat_reports/tests/test_vat_reports.py
odoo/addons/l10n_be_vat_reports/views/report_vatintraprint.xml
odoo/addons/l10n_be_vat_reports/views/report_vatpartnerlisting.xml
odoo/addons/l10n_be_vat_reports/wizard/__init__.py
odoo/addons/l10n_be_vat_reports/wizard/l10n_be_vat_intra.py
odoo/addons/l10n_be_vat_reports/wizard/l10n_be_vat_intra_client.py
odoo/addons/l10n_be_vat_reports/wizard/l10n_be_vat_intra_view.xml
odoo/addons/l10n_be_vat_reports/wizard/partner_vat_list.py
odoo/addons/l10n_be_vat_reports/wizard/partner_vat_list_client.py
odoo/addons/l10n_be_vat_reports/wizard/partner_vat_list_views.xml
odoo/addons/l10n_be_vat_reports/wizard/vat_declaration_mixin.py
odoo14_addon_l10n_be_vat_reports-14.0.1.1.0.dist-info/METADATA
odoo14_addon_l10n_be_vat_reports-14.0.1.1.0.dist-info/WHEEL
odoo14_addon_l10n_be_vat_reports-14.0.1.1.0.dist-info/top_level.txt
odoo14_addon_l10n_be_vat_reports-14.0.1.1.0.dist-info/RECORD
